click_repl/__init__.py
click_repl/_completer.py
click_repl/_ctx_stack.py
click_repl/_repl.py
click_repl/core.py
click_repl/exceptions.py
click_repl/globals_.py
click_repl/utils.py
sereto_repl-0.3.1.dist-info/LICENSE
sereto_repl-0.3.1.dist-info/METADATA
sereto_repl-0.3.1.dist-info/WHEEL
sereto_repl-0.3.1.dist-info/top_level.txt
sereto_repl-0.3.1.dist-info/RECORD
