Metadata-Version: 2.2
Name: sereto-repl
Version: 0.3.1
Summary: REPL plugin for Click
Home-page: https://github.com/click-contrib/click-repl
Author: Markus Unterwaditzer
Author-email: markus@unterwaditzer.net
License: MIT
Classifier: Programming Language :: Python :: 3
Classifier: Programming Language :: Python :: 3 :: Only
Classifier: Programming Language :: Python :: 3.6
Classifier: Programming Language :: Python :: 3.7
Classifier: Programming Language :: Python :: 3.8
Classifier: Programming Language :: Python :: 3.9
Classifier: Programming Language :: Python :: 3.10
Classifier: Programming Language :: Python :: 3.11
Requires-Python: >=3.6
License-File: LICENSE
Requires-Dist: click>=7.0
Requires-Dist: prompt_toolkit>=3.0.36
Requires-Dist: typing-extensions>=4.7.0
Provides-Extra: testing
Requires-Dist: pytest>=7.2.1; extra == "testing"
Requires-Dist: pytest-cov>=4.0.0; extra == "testing"
Requires-Dist: tox>=4.4.3; extra == "testing"
